pudim_hunter_driver_scraper/__init__.py
pudim_hunter_driver_scraper/_version.py
pudim_hunter_driver_scraper/driver.py
pudim_hunter_driver_scraper/scraper.py
pudim_hunter_driver_scraper/scraper_phantom.py
pudim_hunter_driver_scraper-1.0.1.dist-info/LICENSE.md
pudim_hunter_driver_scraper-1.0.1.dist-info/METADATA
pudim_hunter_driver_scraper-1.0.1.dist-info/WHEEL
pudim_hunter_driver_scraper-1.0.1.dist-info/top_level.txt
pudim_hunter_driver_scraper-1.0.1.dist-info/RECORD
