Metadata-Version: 2.1
Name: pudim-hunter-driver-scraper
Version: 1.0.1
Summary: Playwright-based scraper implementation for The Pudim Hunter platform
Author-email: The Pudim Hunter Team <luis.reis@gmail.com>
License: MIT
Project-URL: Source, https://github.com/luismr/pudim-hunter-driver-scraper
Project-URL: Bug Tracker, https://github.com/luismr/pudim-hunter-driver-scraper/issues
Classifier: Development Status :: 3 - Alpha
Classifier: Intended Audience :: Developers
Classifier: Operating System :: OS Independent
Classifier: Programming Language :: Python :: 3
Classifier: Programming Language :: Python :: 3.9
Classifier: Topic :: Software Development :: Libraries :: Python Modules
Requires-Python: >=3.9
License-File: LICENSE.md
Requires-Dist: pudim-hunter-driver>=1.0.0
Requires-Dist: playwright>=1.41.0
Requires-Dist: pydantic>=2.0.0
Requires-Dist: pytest>=7.4.0
Requires-Dist: pytest-asyncio>=0.21.0
Requires-Dist: pytest-cov>=4.1.0
Requires-Dist: black>=23.0.0
Requires-Dist: flake8>=6.0.0
Requires-Dist: mypy>=1.0.0
Requires-Dist: isort>=5.12.0
Requires-Dist: wheel>=0.40.0
Requires-Dist: setuptools==69.2.0
Requires-Dist: setuptools-scm[toml]==8.0.0
Requires-Dist: twine>=4.0.2
Requires-Dist: build>=1.0.3
